odoo/addons/sale_product_matrix_secondary_unit/README.rst
odoo/addons/sale_product_matrix_secondary_unit/__init__.py
odoo/addons/sale_product_matrix_secondary_unit/__manifest__.py
odoo/addons/sale_product_matrix_secondary_unit/i18n/it.po
odoo/addons/sale_product_matrix_secondary_unit/i18n/sale_product_matrix_secondary_unit.pot
odoo/addons/sale_product_matrix_secondary_unit/models/__init__.py
odoo/addons/sale_product_matrix_secondary_unit/models/product_template.py
odoo/addons/sale_product_matrix_secondary_unit/models/sale_order.py
odoo/addons/sale_product_matrix_secondary_unit/readme/CONFIGURE.md
odoo/addons/sale_product_matrix_secondary_unit/readme/CONTRIBUTORS.md
odoo/addons/sale_product_matrix_secondary_unit/readme/DESCRIPTION.md
odoo/addons/sale_product_matrix_secondary_unit/readme/ROADMAP.md
odoo/addons/sale_product_matrix_secondary_unit/readme/USAGE.md
odoo/addons/sale_product_matrix_secondary_unit/static/description/icon.png
odoo/addons/sale_product_matrix_secondary_unit/static/description/index.html
odoo/addons/sale_product_matrix_secondary_unit/static/src/js/product_matrix_dialog.esm.js
odoo/addons/sale_product_matrix_secondary_unit/static/src/js/sale_product_field.esm.js
odoo/addons/sale_product_matrix_secondary_unit/static/src/xml/product_matrix.xml
odoo/addons/sale_product_matrix_secondary_unit/static/src/xml/product_matrix_dialog.xml
odoo/addons/sale_product_matrix_secondary_unit/static/tests/tours/sale_product_matrix_secondary_unit_tour.esm.js
odoo/addons/sale_product_matrix_secondary_unit/tests/__init__.py
odoo/addons/sale_product_matrix_secondary_unit/tests/test_sale_product_matrix_secondary_unit.py
odoo/addons/sale_product_matrix_secondary_unit/views/sale_order_views.xml
odoo_addon_sale_product_matrix_secondary_unit-17.0.1.0.0.4.dist-info/METADATA
odoo_addon_sale_product_matrix_secondary_unit-17.0.1.0.0.4.dist-info/WHEEL
odoo_addon_sale_product_matrix_secondary_unit-17.0.1.0.0.4.dist-info/top_level.txt
odoo_addon_sale_product_matrix_secondary_unit-17.0.1.0.0.4.dist-info/RECORD
